YaocaoYumofa/README.md
YaocaoYumofa/__init__.py
YaocaoYumofa/__main__.py
YaocaoYumofa/file.epub
YaocaoYumofa/index.html
YaocaoYumofa/css/__init__.py
YaocaoYumofa/css/annotations.css
YaocaoYumofa/css/main.css
YaocaoYumofa/css/normalize.css
YaocaoYumofa/css/popup.css
YaocaoYumofa/font/__init__.py
YaocaoYumofa/font/fontello.eot
YaocaoYumofa/font/fontello.svg
YaocaoYumofa/font/fontello.ttf
YaocaoYumofa/font/fontello.woff
YaocaoYumofa/img/__init__.py
YaocaoYumofa/img/annotator-glyph-sprite.png
YaocaoYumofa/img/annotator-icon-sprite.png
YaocaoYumofa/img/apple-touch-icon.png
YaocaoYumofa/img/cancelfullscreen.png
YaocaoYumofa/img/close.png
YaocaoYumofa/img/fullscreen.png
YaocaoYumofa/img/loader.gif
YaocaoYumofa/img/menu-icon.png
YaocaoYumofa/img/save.png
YaocaoYumofa/img/saved.png
YaocaoYumofa/img/settings-s.png
YaocaoYumofa/img/settings.png
YaocaoYumofa/img/star.png
YaocaoYumofa/js/__init__.py
YaocaoYumofa/js/epub.js
YaocaoYumofa/js/epub.min.js
YaocaoYumofa/js/epub.min.map
YaocaoYumofa/js/hooks.min.js
YaocaoYumofa/js/hooks.min.map
YaocaoYumofa/js/reader.js
YaocaoYumofa/js/reader.js.map
YaocaoYumofa/js/reader.min.js
YaocaoYumofa/js/reader.min.map
YaocaoYumofa/js/hooks/__init__.py
YaocaoYumofa/js/hooks/extensions/__init__.py
YaocaoYumofa/js/hooks/extensions/highlight.js
YaocaoYumofa/js/libs/__init__.py
YaocaoYumofa/js/libs/jquery.min.js
YaocaoYumofa/js/libs/localforage.min.js
YaocaoYumofa/js/libs/screenfull.js
YaocaoYumofa/js/libs/screenfull.min.js
YaocaoYumofa/js/libs/zip.min.js
YaocaoYumofa/js/plugins/__init__.py
YaocaoYumofa/js/plugins/hypothesis.js
YaocaoYumofa/js/plugins/search.js
yaocao_yumofa-2022.9.29.0.dist-info/METADATA
yaocao_yumofa-2022.9.29.0.dist-info/WHEEL
yaocao_yumofa-2022.9.29.0.dist-info/entry_points.txt
yaocao_yumofa-2022.9.29.0.dist-info/top_level.txt
yaocao_yumofa-2022.9.29.0.dist-info/RECORD
